Metadata-Version: 2.4
Name: llm-fragments-pdf
Version: 0.1
Summary: Use PyMuPDF to insert PDFs as markdown
Author: Dan Turkel, Simon Willison
License-Expression: Apache-2.0
Project-URL: Homepage, https://github.com/daturkel/llm-fragments-pdf
Project-URL: Changelog, https://github.com/daturkel/llm-fragments-pdf/releases
Project-URL: Issues, https://github.com/daturkel/llm-fragments-pdf/issues
Project-URL: CI, https://github.com/daturkel/llm-fragments-pdf/actions
Requires-Python: >=3.9
License-File: LICENSE
Requires-Dist: llm
Requires-Dist: pymupdf4llm>=0.0.24
Provides-Extra: test
Requires-Dist: pytest; extra == "test"
Dynamic: license-file
